vito/__init__.py
vito/sas/__init__.py
vito/sas/air/__init__.py
vito/sas/air/api_client.py
vito/sas/air/cams_client.py
vito/sas/air/cams_ftp_client.py
vito/sas/air/ircel_wfs_client.py
vito/sas/air/issep_client.py
vito/sas/air/sos_client.py
vito/sas/air/sos_client_v1.py
vito/sas/air/utils/__init__.py
vito/sas/air/utils/cams_utils.py
vito/sas/air/utils/config_utils.py
vito/sas/air/utils/date_utils.py
vito/sas/air/utils/digest.py
vito/sas/air/utils/remote_io.py
sasair-0.4.1.dist-info/LICENSE.md
sasair-0.4.1.dist-info/METADATA
sasair-0.4.1.dist-info/WHEEL
sasair-0.4.1.dist-info/RECORD
